{"泉州":{"city":"泉州","AQI":"17","quality":"优","pollutant":"","PM2.5":"9","PM10":"11","CO":"0.8","NO2":"25","O3":"53","O3_8h":"28","SO2":"7"},"伊春":{"city":"伊春","AQI":"19","quality":"优","pollutant":"","PM2.5":"5","PM10":"12","CO":"0.25","NO2":"5","O3":"42","O3_8h":"37","SO2":"5"},"龙岩":{"city":"龙岩","AQI":"21","quality":"优","pollutant":"","PM2.5":"11","PM10":"15","CO":"0.975","NO2":"41","O3":"27","O3_8h":"36","SO2":"6"},"佳木斯":{"city":"佳木斯","AQI":"21","quality":"优","pollutant":"","PM2.5":"10","PM10":"12","CO":"0.54","NO2":"16","O3":"40","O3_8h":"40","SO2":"7"},"绥化":{"city":"绥化","AQI":"21","quality":"优","pollutant":"","PM2.5":"6","PM10":"13","CO":"0.4","NO2":"14","O3":"46","O3_8h":"41","SO2":"11"},"大兴安岭地区":{"city":"大兴安岭地区","AQI":"21","quality":"优","pollutant":"","PM2.5":"11","PM10":"5","CO":"0.6","NO2":"11","O3":"60","O3_8h":"40","SO2":"25"},"牡丹江":{"city":"牡丹江","AQI":"22","quality":"优","pollutant":"","PM2.5":"12","PM10":"21","CO":"0.32","NO2":"16","O3":"49","O3_8h":"41","SO2":"4"},"七台河":{"city":"七台河","AQI":"23","quality":"优","pollutant":"","PM2.5":"12","PM10":"14","CO":"0.333","NO2":"12","O3":"36","O3_8h":"44","SO2":"9"},"赤峰":{"city":"赤峰","AQI":"24","quality":"优","pollutant":"","PM2.5":"11","PM10":"15","CO":"0.933","NO2":"13","O3":"52","O3_8h":"47","SO2":"7"},"黔东南州":{"city":"黔东南州","AQI":"24","quality":"优","pollutant":"","PM2.5":"14","PM10":"18","CO":"0.5","NO2":"16","O3":"74","O3_8h":"45","SO2":"4"},"盘锦":{"city":"盘锦","AQI":"25","quality":"优","pollutant":"","PM2.5":"7","PM10":"12","CO":"0.7","NO2":"15","O3":"63","O3_8h":"48","SO2":"9"},"三明":{"city":"三明","AQI":"25","quality":"优","pollutant":"","PM2.5":"9","PM10":"20","CO":"0.725","NO2":"15","O3":"59","O3_8h":"49","SO2":"7"},"瓦房店":{"city":"瓦房店","AQI":"25","quality":"优","pollutant":"","PM2.5":"10","PM10":"18","CO":"0.15","NO2":"14","O3":"73","O3_8h":"48","SO2":"3"},"营口":{"city":"营口","AQI":"25","quality":"优","pollutant":"","PM2.5":"8","PM10":"17","CO":"0.2","NO2":"12","O3":"77","O3_8h":"44","SO2":"7"},"鹤岗":{"city":"鹤岗","AQI":"25","quality":"优","pollutant":"","PM2.5":"7","PM10":"15","CO":"0.325","NO2":"6","O3":"44","O3_8h":"48","SO2":"3"},"白山":{"city":"白山","AQI":"26","quality":"优","pollutant":"","PM2.5":"8","PM10":"20","CO":"0.7","NO2":"11","O3":"64","O3_8h":"50","SO2":"3"},"黑河":{"city":"黑河","AQI":"26","quality":"优","pollutant":"","PM2.5":"9","PM10":"16","CO":"0.333","NO2":"12","O3":"61","O3_8h":"51","SO2":"11"},"鸡西":{"city":"鸡西","AQI":"26","quality":"优","pollutant":"","PM2.5":"18","PM10":"18","CO":"0.25","NO2":"10","O3":"41","O3_8h":"44","SO2":"2"},"秦皇岛":{"city":"秦皇岛","AQI":"27","quality":"优","pollutant":"","PM2.5":"8","PM10":"18","CO":"0.34","NO2":"17","O3":"71","O3_8h":"53","SO2":"7"},"葫芦岛":{"city":"葫芦岛","AQI":"27","quality":"优","pollutant":"","PM2.5":"10","PM10":"13","CO":"0.825","NO2":"21","O3":"62","O3_8h":"53","SO2":"11"},"通化":{"city":"通化","AQI":"27","quality":"优","pollutant":"","PM2.5":"5","PM10":"14","CO":"0.85","NO2":"14","O3":"64","O3_8h":"53","SO2":"4"},"阜新":{"city":"阜新","AQI":"28","quality":"优","pollutant":"","PM2.5":"6","PM10":"20","CO":"0.3","NO2":"7","O3":"78","O3_8h":"55","SO2":"3"},"怒江州":{"city":"怒江州","AQI":"28","quality":"优","pollutant":"","PM2.5":"12","PM10":"16","CO":"1.3","NO2":"8","O3":"88","O3_8h":"54","SO2":"10"},"本溪":{"city":"本溪","AQI":"28","quality":"优","pollutant":"","PM2.5":"7","PM10":"27","CO":"0.533","NO2":"23","O3":"55","O3_8h":"40","SO2":"11"},"辽阳":{"city":"辽阳","AQI":"28","quality":"优","pollutant":"","PM2.5":"5","PM10":"27","CO":"0.225","NO2":"7","O3":"84","O3_8h":"50","SO2":"6"},"韶关":{"city":"韶关","AQI":"28","quality":"优","pollutant":"","PM2.5":"19","PM10":"15","CO":"1.12","NO2":"15","O3":"51","O3_8h":"37","SO2":"30"},"阿坝州":{"city":"阿坝州","AQI":"28","quality":"优","pollutant":"","PM2.5":"4","PM10":"5","CO":"0.45","NO2":"3","O3":"88","O3_8h":"55","SO2":"8"},"长春":{"city":"长春","AQI":"28","quality":"优","pollutant":"","PM2.5":"9","PM10":"18","CO":"0.74","NO2":"15","O3":"63","O3_8h":"54","SO2":"10"},"辽源":{"city":"辽源","AQI":"28","quality":"优","pollutant":"","PM2.5":"8","PM10":"18","CO":"0.45","NO2":"12","O3":"75","O3_8h":"55","SO2":"7"},"双鸭山":{"city":"双鸭山","AQI":"29","quality":"优","pollutant":"","PM2.5":"12","PM10":"23","CO":"0.325","NO2":"6","O3":"56","O3_8h":"56","SO2":"3"},"抚顺":{"city":"抚顺","AQI":"29","quality":"优","pollutant":"","PM2.5":"11","PM10":"20","CO":"0.267","NO2":"12","O3":"76","O3_8h":"57","SO2":"8"},"三亚":{"city":"三亚","AQI":"29","quality":"优","pollutant":"","PM2.5":"10","PM10":"27","CO":"0.45","NO2":"4","O3":"48","O3_8h":"57","SO2":"1"},"萍乡":{"city":"萍乡","AQI":"29","quality":"优","pollutant":"","PM2.5":"19","PM10":"24","CO":"1.18","NO2":"13","O3":"91","O3_8h":"48","SO2":"12"},"德宏州":{"city":"德宏州","AQI":"30","quality":"优","pollutant":"","PM2.5":"17","PM10":"29","CO":"0.6","NO2":"10","O3":"70","O3_8h":"40","SO2":"14"},"三沙":{"city":"三沙","AQI":"30","quality":"优","pollutant":"","PM2.5":"7","PM10":"20","CO":"0.3","NO2":"30","O3":"51","O3_8h":"58","SO2":"6"},"吉林":{"city":"吉林","AQI":"30","quality":"优","pollutant":"","PM2.5":"17","PM10":"29","CO":"0.557","NO2":"24","O3":"57","O3_8h":"38","SO2":"20"},"沈阳":{"city":"沈阳","AQI":"30","quality":"优","pollutant":"","PM2.5":"10","PM10":"29","CO":"0.309","NO2":"11","O3":"89","O3_8h":"56","SO2":"6"},"河池":{"city":"河池","AQI":"31","quality":"优","pollutant":"","PM2.5":"12","PM10":"28","CO":"0.6","NO2":"8","O3":"95","O3_8h":"61","SO2":"9"},"南平":{"city":"南平","AQI":"31","quality":"优","pollutant":"","PM2.5":"4","PM10":"8","CO":"0.65","NO2":"8","O3":"61","O3_8h":"61","SO2":"3"},"铁岭":{"city":"铁岭","AQI":"31","quality":"优","pollutant":"","PM2.5":"7","PM10":"23","CO":"0.525","NO2":"9","O3":"84","O3_8h":"61","SO2":"12"},"哈尔滨":{"city":"哈尔滨","AQI":"31","quality":"优","pollutant":"","PM2.5":"17","PM10":"30","CO":"0.473","NO2":"21","O3":"79","O3_8h":"58","SO2":"9"},"丹东":{"city":"丹东","AQI":"31","quality":"优","pollutant":"","PM2.5":"9","PM10":"30","CO":"0.867","NO2":"17","O3":"76","O3_8h":"55","SO2":"10"},"贺州":{"city":"贺州","AQI":"32","quality":"优","pollutant":"","PM2.5":"10","PM10":"27","CO":"0.9","NO2":"7","O3":"86","O3_8h":"62","SO2":"8"},"塔城地区":{"city":"塔城地区","AQI":"32","quality":"优","pollutant":"","PM2.5":"8","PM10":"18","CO":"1.0","NO2":"7","O3":"95","O3_8h":"63","SO2":"6"},"潮州":{"city":"潮州","AQI":"32","quality":"优","pollutant":"","PM2.5":"22","PM10":"27","CO":"0.8","NO2":"7","O3":"74","O3_8h":"47","SO2":"8"},"朝阳":{"city":"朝阳","AQI":"32","quality":"优","pollutant":"","PM2.5":"4","PM10":"5","CO":"0.525","NO2":"10","O3":"71","O3_8h":"62","SO2":"9"},"珠海":{"city":"珠海","AQI":"32","quality":"优","pollutant":"","PM2.5":"14","PM10":"31","CO":"0.575","NO2":"5","O3":"62","O3_8h":"51","SO2":"3"},"松原":{"city":"松原","AQI":"32","quality":"优","pollutant":"","PM2.5":"8","PM10":"27","CO":"0.95","NO2":"5","O3":"80","O3_8h":"63","SO2":"4"},"通辽":{"city":"通辽","AQI":"32","quality":"优","pollutant":"","PM2.5":"12","PM10":"10","CO":"0.2","NO2":"6","O3":"72","O3_8h":"62","SO2":"4"},"永州":{"city":"永州","AQI":"33","quality":"优","pollutant":"","PM2.5":"10","PM10":"26","CO":"0.48","NO2":"13","O3":"90","O3_8h":"65","SO2":"3"},"伊犁哈萨克州":{"city":"伊犁哈萨克州","AQI":"33","quality":"优","pollutant":"","PM2.5":"20","PM10":"25","CO":"0.733","NO2":"11","O3":"91","O3_8h":"65","SO2":"9"},"承德":{"city":"承德","AQI":"34","quality":"优","pollutant":"","PM2.5":"17","PM10":"24","CO":"0.4","NO2":"9","O3":"77","O3_8h":"67","SO2":"6"},"宁德":{"city":"宁德","AQI":"34","quality":"优","pollutant":"","PM2.5":"7","PM10":"10","CO":"0.733","NO2":"16","O3":"81","O3_8h":"67","SO2":"2"},"白城":{"city":"白城","AQI":"34","quality":"优","pollutant":"","PM2.5":"10","PM10":"22","CO":"0.35","NO2":"16","O3":"90","O3_8h":"66","SO2":"6"},"阳江":{"city":"阳江","AQI":"34","quality":"优","pollutant":"","PM2.5":"20","PM10":"33","CO":"0.667","NO2":"5","O3":"84","O3_8h":"62","SO2":"5"},"赣州":{"city":"赣州","AQI":"34","quality":"优","pollutant":"","PM2.5":"23","PM10":"33","CO":"1.16","NO2":"12","O3":"87","O3_8h":"61","SO2":"17"},"延边州":{"city":"延边州","AQI":"34","quality":"优","pollutant":"","PM2.5":"4","PM10":"11","CO":"0.667","NO2":"13","O3":"75","O3_8h":"67","SO2":"8"},"齐齐哈尔":{"city":"齐齐哈尔","AQI":"34","quality":"优","pollutant":"","PM2.5":"9","PM10":"22","CO":"0.48","NO2":"17","O3":"81","O3_8h":"66","SO2":"8"},"桂林":{"city":"桂林","AQI":"34","quality":"优","pollutant":"","PM2.5":"14","PM10":"26","CO":"0.525","NO2":"16","O3":"73","O3_8h":"67","SO2":"7"},"大庆":{"city":"大庆","AQI":"34","quality":"优","pollutant":"","PM2.5":"8","PM10":"14","CO":"0.38","NO2":"10","O3":"97","O3_8h":"66","SO2":"4"},"大连":{"city":"大连","AQI":"34","quality":"优","pollutant":"","PM2.5":"9","PM10":"31","CO":"0.58","NO2":"22","O3":"73","O3_8h":"66","SO2":"6"},"四平":{"city":"四平","AQI":"35","quality":"优","pollutant":"","PM2.5":"10","PM10":"27","CO":"0.333","NO2":"7","O3":"83","O3_8h":"68","SO2":"10"},"梅州":{"city":"梅州","AQI":"35","quality":"优","pollutant":"","PM2.5":"15","PM10":"34","CO":"0.85","NO2":"14","O3":"68","O3_8h":"52","SO2":"5"},"莆田":{"city":"莆田","AQI":"36","quality":"优","pollutant":"","PM2.5":"6","PM10":"10","CO":"0.68","NO2":"13","O3":"90","O3_8h":"71","SO2":"7"},"福州":{"city":"福州","AQI":"36","quality":"优","pollutant":"","PM2.5":"7","PM10":"14","CO":"0.683","NO2":"24","O3":"79","O3_8h":"70","SO2":"4"},"乳山":{"city":"乳山","AQI":"37","quality":"优","pollutant":"","PM2.5":"4","PM10":"29","CO":"0.3","NO2":"14","O3":"100","O3_8h":"73","SO2":"5"},"玉溪":{"city":"玉溪","AQI":"37","quality":"优","pollutant":"","PM2.5":"13","PM10":"20","CO":"0.567","NO2":"8","O3":"97","O3_8h":"72","SO2":"8"},"茂名":{"city":"茂名","AQI":"37","quality":"优","pollutant":"","PM2.5":"14","PM10":"36","CO":"0.55","NO2":"8","O3":"94","O3_8h":"68","SO2":"6"},"乌鲁木齐":{"city":"乌鲁木齐","AQI":"37","quality":"优","pollutant":"","PM2.5":"19","PM10":"36","CO":"0.443","NO2":"16","O3":"81","O3_8h":"54","SO2":"7"},"深圳":{"city":"深圳","AQI":"38","quality":"优","pollutant":"","PM2.5":"17","PM10":"37","CO":"0.682","NO2":"19","O3":"64","O3_8h":"50","SO2":"6"},"文山州":{"city":"文山州","AQI":"38","quality":"优","pollutant":"","PM2.5":"15","PM10":"26","CO":"0.45","NO2":"6","O3":"108","O3_8h":"74","SO2":"10"},"锦州":{"city":"锦州","AQI":"38","quality":"优","pollutant":"","PM2.5":"13","PM10":"37","CO":"0.68","NO2":"25","O3":"54","O3_8h":"48","SO2":"8"},"昌都地区":{"city":"昌都地区","AQI":"38","quality":"优","pollutant":"","PM2.5":"5","PM10":"27","CO":"1.15","NO2":"6","O3":"118","O3_8h":"69","SO2":"6"},"北海":{"city":"北海","AQI":"38","quality":"优","pollutant":"","PM2.5":"14","PM10":"33","CO":"0.8","NO2":"4","O3":"100","O3_8h":"75","SO2":"7"},"贵港":{"city":"贵港","AQI":"38","quality":"优","pollutant":"","PM2.5":"13","PM10":"31","CO":"0.75","NO2":"15","O3":"109","O3_8h":"74","SO2":"6"},"大理州":{"city":"大理州","AQI":"38","quality":"优","pollutant":"","PM2.5":"16","PM10":"23","CO":"0.8","NO2":"14","O3":"106","O3_8h":"75","SO2":"7"},"凉山州":{"city":"凉山州","AQI":"38","quality":"优","pollutant":"","PM2.5":"21","PM10":"37","CO":"0.56","NO2":"13","O3":"97","O3_8h":"50","SO2":"9"},"昌吉州":{"city":"昌吉州","AQI":"39","quality":"优","pollutant":"","PM2.5":"11","PM10":"38","CO":"0.567","NO2":"19","O3":"85","O3_8h":"62","SO2":"5"},"兴安盟":{"city":"兴安盟","AQI":"39","quality":"优","pollutant":"","PM2.5":"14","PM10":"38","CO":"0.367","NO2":"9","O3":"70","O3_8h":"58","SO2":"2"},"郴州":{"city":"郴州","AQI":"39","quality":"优","pollutant":"","PM2.5":"14","PM10":"27","CO":"1.12","NO2":"9","O3":"108","O3_8h":"77","SO2":"5"},"西双版纳州":{"city":"西双版纳州","AQI":"40","quality":"优","pollutant":"","PM2.5":"15","PM10":"39","CO":"0.35","NO2":"6","O3":"95","O3_8h":"63","SO2":"8"},"柳州":{"city":"柳州","AQI":"40","quality":"优","pollutant":"","PM2.5":"24","PM10":"39","CO":"1.033","NO2":"14","O3":"98","O3_8h":"67","SO2":"18"},"鞍山":{"city":"鞍山","AQI":"40","quality":"优","pollutant":"","PM2.5":"18","PM10":"39","CO":"0.543","NO2":"20","O3":"53","O3_8h":"34","SO2":"11"},"克拉玛依":{"city":"克拉玛依","AQI":"40","quality":"优","pollutant":"","PM2.5":"10","PM10":"39","CO":"0.8","NO2":"9","O3":"93","O3_8h":"59","SO2":"5"},"呼伦贝尔":{"city":"呼伦贝尔","AQI":"41","quality":"优","pollutant":"","PM2.5":"8","PM10":"40","CO":"0.15","NO2":"6","O3":"87","O3_8h":"72","SO2":"1"},"楚雄州":{"city":"楚雄州","AQI":"41","quality":"优","pollutant":"","PM2.5":"8","PM10":"12","CO":"0.75","NO2":"6","O3":"92","O3_8h":"81","SO2":"14"},"阿勒泰地区":{"city":"阿勒泰地区","AQI":"41","quality":"优","pollutant":"","PM2.5":"7","PM10":"40","CO":"0.35","NO2":"6","O3":"82","O3_8h":"59","SO2":"4"},"毕节":{"city":"毕节","AQI":"41","quality":"优","pollutant":"","PM2.5":"15","PM10":"36","CO":"0.85","NO2":"10","O3":"130","O3_8h":"76","SO2":"9"},"昆明":{"city":"昆明","AQI":"42","quality":"优","pollutant":"","PM2.5":"12","PM10":"32","CO":"0.657","NO2":"12","O3":"100","O3_8h":"82","SO2":"11"},"邵阳":{"city":"邵阳","AQI":"42","quality":"优","pollutant":"","PM2.5":"18","PM10":"31","CO":"0.48","NO2":"4","O3":"133","O3_8h":"78","SO2":"11"},"衡阳":{"city":"衡阳","AQI":"42","quality":"优","pollutant":"","PM2.5":"29","PM10":"41","CO":"0.933","NO2":"10","O3":"118","O3_8h":"71","SO2":"7"},"来宾":{"city":"来宾","AQI":"42","quality":"优","pollutant":"","PM2.5":"19","PM10":"41","CO":"0.95","NO2":"13","O3":"108","O3_8h":"60","SO2":"14"},"益阳":{"city":"益阳","AQI":"43","quality":"优","pollutant":"","PM2.5":"22","PM10":"42","CO":"0.78","NO2":"10","O3":"136","O3_8h":"85","SO2":"7"},"鹰潭":{"city":"鹰潭","AQI":"43","quality":"优","pollutant":"","PM2.5":"30","PM10":"39","CO":"0.7","NO2":"6","O3":"106","O3_8h":"81","SO2":"20"},"黔南州":{"city":"黔南州","AQI":"43","quality":"优","pollutant":"","PM2.5":"30","PM10":"40","CO":"0.6","NO2":"8","O3":"69","O3_8h":"48","SO2":"5"},"海口":{"city":"海口","AQI":"43","quality":"优","pollutant":"","PM2.5":"15","PM10":"42","CO":"0.46","NO2":"6","O3":"66","O3_8h":"48","SO2":"5"},"宜春":{"city":"宜春","AQI":"44","quality":"优","pollutant":"","PM2.5":"29","PM10":"43","CO":"0.68","NO2":"5","O3":"122","O3_8h":"84","SO2":"12"},"厦门":{"city":"厦门","AQI":"44","quality":"优","pollutant":"","PM2.5":"23","PM10":"43","CO":"0.375","NO2":"11","O3":"41","O3_8h":"25","SO2":"4"},"哈密地区":{"city":"哈密地区","AQI":"44","quality":"优","pollutant":"","PM2.5":"20","PM10":"36","CO":"0.9","NO2":"9","O3":"107","O3_8h":"86","SO2":"14"},"荣成":{"city":"荣成","AQI":"44","quality":"优","pollutant":"","PM2.5":"7","PM10":"43","CO":"0.35","NO2":"12","O3":"83","O3_8h":"71","SO2":"9"},"文登":{"city":"文登","AQI":"44","quality":"优","pollutant":"","PM2.5":"6","PM10":"43","CO":"0.25","NO2":"11","O3":"90","O3_8h":"72","SO2":"5"},"蓬莱":{"city":"蓬莱","AQI":"45","quality":"优","pollutant":"","PM2.5":"14","PM10":"44","CO":"0.7","NO2":"21","O3":"86","O3_8h":"67","SO2":"12"},"清远":{"city":"清远","AQI":"45","quality":"优","pollutant":"","PM2.5":"29","PM10":"44","CO":"0.833","NO2":"25","O3":"101","O3_8h":"30","SO2":"11"},"玉林":{"city":"玉林","AQI":"45","quality":"优","pollutant":"","PM2.5":"23","PM10":"44","CO":"0.667","NO2":"5","O3":"95","O3_8h":"62","SO2":"7"},"锡林郭勒盟":{"city":"锡林郭勒盟","AQI":"46","quality":"优","pollutant":"","PM2.5":"13","PM10":"11","CO":"0.7","NO2":"10","O3":"92","O3_8h":"90","SO2":"9"},"海门":{"city":"海门","AQI":"46","quality":"优","pollutant":"","PM2.5":"15","PM10":"35","CO":"0.433","NO2":"9","O3":"97","O3_8h":"91","SO2":"12"},"林芝地区":{"city":"林芝地区","AQI":"46","quality":"优","pollutant":"","PM2.5":"32","PM10":"16","CO":"0.3","NO2":"5","O3":"110","O3_8h":"86","SO2":"3"},"甘孜州":{"city":"甘孜州","AQI":"47","quality":"优","pollutant":"","PM2.5":"17","PM10":"46","CO":"0.15","NO2":"13","O3":"80","O3_8h":"59","SO2":"23"},"博州":{"city":"博州","AQI":"47","quality":"优","pollutant":"","PM2.5":"28","PM10":"46","CO":"0.7","NO2":"10","O3":"116","O3_8h":"65","SO2":"5"},"红河州":{"city":"红河州","AQI":"47","quality":"优","pollutant":"","PM2.5":"20","PM10":"46","CO":"0.4","NO2":"3","O3":"109","O3_8h":"90","SO2":"9"},"肇庆":{"city":"肇庆","AQI":"47","quality":"优","pollutant":"","PM2.5":"25","PM10":"46","CO":"0.65","NO2":"10","O3":"88","O3_8h":"54","SO2":"6"},"普洱":{"city":"普洱","AQI":"47","quality":"优","pollutant":"","PM2.5":"26","PM10":"46","CO":"0.35","NO2":"9","O3":"90","O3_8h":"65","SO2":"4"},"南昌":{"city":"南昌","AQI":"47","quality":"优","pollutant":"","PM2.5":"24","PM10":"46","CO":"0.878","NO2":"10","O3":"127","O3_8h":"91","SO2":"7"},"定西":{"city":"定西","AQI":"48","quality":"优","pollutant":"","PM2.5":"19","PM10":"37","CO":"0.3","NO2":"8","O3":"134","O3_8h":"94","SO2":"5"},"佛山":{"city":"佛山","AQI":"48","quality":"优","pollutant":"","PM2.5":"24","PM10":"47","CO":"0.638","NO2":"11","O3":"121","O3_8h":"64","SO2":"8"},"汕头":{"city":"汕头","AQI":"48","quality":"优","pollutant":"","PM2.5":"19","PM10":"47","CO":"0.533","NO2":"4","O3":"60","O3_8h":"51","SO2":"6"},"抚州":{"city":"抚州","AQI":"48","quality":"优","pollutant":"","PM2.5":"33","PM10":"46","CO":"0.78","NO2":"5","O3":"124","O3_8h":"89","SO2":"13"},"陇南":{"city":"陇南","AQI":"49","quality":"优","pollutant":"","PM2.5":"17","PM10":"45","CO":"0.55","NO2":"7","O3":"125","O3_8h":"97","SO2":"20"},"海西州":{"city":"海西州","AQI":"49","quality":"优","pollutant":"","PM2.5":"10","PM10":"11","CO":"0.7","NO2":"12","O3":"98","O3_8h":"97","SO2":"23"},"安顺":{"city":"安顺","AQI":"49","quality":"优","pollutant":"","PM2.5":"21","PM10":"32","CO":"0.575","NO2":"7","O3":"124","O3_8h":"96","SO2":"9"},"湛江":{"city":"湛江","AQI":"50","quality":"优","pollutant":"颗粒物(PM10)","PM2.5":"14","PM10":"49","CO":"0.55","NO2":"7","O3":"80","O3_8h":"57","SO2":"7"},"台州":{"city":"台州","AQI":"50","quality":"优","pollutant":"颗粒物(PM10)","PM2.5":"34","PM10":"49","CO":"0.5","NO2":"10","O3":"119","O3_8h":"92","SO2":"3"},"义乌":{"city":"义乌","AQI":"50","quality":"优","pollutant":"颗粒物(PM2.5)颗粒物(PM10)","PM2.5":"35","PM10":"49","CO":"0.7","NO2":"12","O3":"148","O3_8h":"94","SO2":"9"},"果洛州":{"city":"果洛州","AQI":"50","quality":"优","pollutant":"臭氧8小时","PM2.5":"14","PM10":"16","CO":"0.7","NO2":"11","O3":"135","O3_8h":"99","SO2":"21"},"石河子":{"city":"石河子","AQI":"50","quality":"优","pollutant":"臭氧8小时","PM2.5":"10","PM10":"25","CO":"0.35","NO2":"27","O3":"101","O3_8h":"99","SO2":"7"},"延安":{"city":"延安","AQI":"50","quality":"优","pollutant":"臭氧8小时臭氧1小时","PM2.5":"22","PM10":"48","CO":"0.925","NO2":"19","O3":"156","O3_8h":"99","SO2":"12"},"廊坊":{"city":"廊坊","AQI":"50","quality":"优","pollutant":"颗粒物(PM10)","PM2.5":"21","PM10":"49","CO":"0.825","NO2":"23","O3":"58","O3_8h":"32","SO2":"5"},"招远":{"city":"招远","AQI":"50","quality":"优","pollutant":"臭氧8小时","PM2.5":"7","PM10":"48","CO":"0.35","NO2":"4","O3":"125","O3_8h":"98","SO2":"7"},"青岛":{"city":"青岛","AQI":"51","quality":"良","pollutant":"颗粒物(PM10)","PM2.5":"11","PM10":"50","CO":"0.333","NO2":"15","O3":"100","O3_8h":"84","SO2":"19"},"崇左":{"city":"崇左","AQI":"51","quality":"良","pollutant":"颗粒物(PM10)","PM2.5":"35","PM10":"50","CO":"0.9","NO2":"10","O3":"139","O3_8h":"79","SO2":"8"},"南宁":{"city":"南宁","AQI":"52","quality":"良","pollutant":"颗粒物(PM10)","PM2.5":"25","PM10":"51","CO":"0.988","NO2":"30","O3":"74","O3_8h":"54","SO2":"8"},"眉山":{"city":"眉山","AQI":"52","quality":"良","pollutant":"颗粒物(PM10)","PM2.5":"24","PM10":"51","CO":"0.6","NO2":"11","O3":"136","O3_8h":"80","SO2":"20"},"云浮":{"city":"云浮","AQI":"52","quality":"良","pollutant":"颗粒物(PM10)","PM2.5":"22","PM10":"52","CO":"0.567","NO2":"2","O3":"87","O3_8h":"60","SO2":"4"},"威海":{"city":"威海","AQI":"52","quality":"良","pollutant":"颗粒物(PM10)","PM2.5":"8","PM10":"52","CO":"0.467","NO2":"22","O3":"83","O3_8h":"65","SO2":"13"},"莱西":{"city":"莱西","AQI":"52","quality":"良","pollutant":"颗粒物(PM10)","PM2.5":"21","PM10":"51","CO":"0.2","NO2":"5","O3":"108","O3_8h":"85","SO2":"4"},"巴中":{"city":"巴中","AQI":"52","quality":"良","pollutant":"颗粒物(PM10)","PM2.5":"32","PM10":"52","CO":"0.65","NO2":"9","O3":"125","O3_8h":"74","SO2":"8"},"惠州":{"city":"惠州","AQI":"52","quality":"良","pollutant":"颗粒物(PM10)","PM2.5":"21","PM10":"51","CO":"0.68","NO2":"14","O3":"85","O3_8h":"55","SO2":"7"},"雅安":{"city":"雅安","AQI":"52","quality":"良","pollutant":"颗粒物(PM10)","PM2.5":"33","PM10":"52","CO":"0.5","NO2":"21","O3":"103","O3_8h":"67","SO2":"10"},"百色":{"city":"百色","AQI":"52","quality":"良","pollutant":"颗粒物(PM10)","PM2.5":"24","PM10":"51","CO":"0.65","NO2":"12","O3":"119","O3_8h":"76","SO2":"3"},"昭通":{"city":"昭通","AQI":"52","quality":"良","pollutant":"臭氧8小时","PM2.5":"15","PM10":"50","CO":"0.45","NO2":"10","O3":"131","O3_8h":"101","SO2":"9"},"连云港":{"city":"连云港","AQI":"53","quality":"良","pollutant":"臭氧8小时","PM2.5":"14","PM10":"52","CO":"0.34","NO2":"16","O3":"118","O3_8h":"102","SO2":"10"},"温州":{"city":"温州","AQI":"53","quality":"良","pollutant":"颗粒物(PM2.5)","PM2.5":"36","PM10":"51","CO":"0.6","NO2":"21","O3":"150","O3_8h":"81","SO2":"8"},"中山":{"city":"中山","AQI":"53","quality":"良","pollutant":"颗粒物(PM10)","PM2.5":"15","PM10":"54","CO":"0.525","NO2":"4","O3":"111","O3_8h":"77","SO2":"5"},"株洲":{"city":"株洲","AQI":"53","quality":"良","pollutant":"颗粒物(PM10)","PM2.5":"33","PM10":"53","CO":"0.686","NO2":"14","O3":"111","O3_8h":"64","SO2":"28"},"临沧":{"city":"临沧","AQI":"53","quality":"良","pollutant":"颗粒物(PM10)","PM2.5":"28","PM10":"54","CO":"0.65","NO2":"11","O3":"93","O3_8h":"44","SO2":"13"},"丽水":{"city":"丽水","AQI":"53","quality":"良","pollutant":"颗粒物(PM10)","PM2.5":"33","PM10":"53","CO":"0.467","NO2":"12","O3":"123","O3_8h":"73","SO2":"7"},"汕尾":{"city":"汕尾","AQI":"53","quality":"良","pollutant":"颗粒物(PM10)","PM2.5":"30","PM10":"54","CO":"0.767","NO2":"4","O3":"83","O3_8h":"55","SO2":"8"},"丽江":{"city":"丽江","AQI":"53","quality":"良","pollutant":"臭氧8小时","PM2.5":"10","PM10":"27","CO":"0.5","NO2":"7","O3":"126","O3_8h":"102","SO2":"6"},"平凉":{"city":"平凉","AQI":"53","quality":"良","pollutant":"颗粒物(PM10)","PM2.5":"20","PM10":"54","CO":"0.3","NO2":"11","O3":"136","O3_8h":"74","SO2":"4"},"攀枝花":{"city":"攀枝花","AQI":"53","quality":"良","pollutant":"颗粒物(PM2.5)","PM2.5":"36","PM10":"38","CO":"1.2","NO2":"16","O3":"105","O3_8h":"70","SO2":"24"},"曲靖":{"city":"曲靖","AQI":"53","quality":"良","pollutant":"颗粒物(PM10)","PM2.5":"27","PM10":"53","CO":"1.0","NO2":"11","O3":"107","O3_8h":"68","SO2":"12"},"泸州":{"city":"泸州","AQI":"54","quality":"良","pollutant":"颗粒物(PM10)","PM2.5":"27","PM10":"56","CO":"0.375","NO2":"12","O3":"140","O3_8h":"63","SO2":"10"},"河源":{"city":"河源","AQI":"54","quality":"良","pollutant":"颗粒物(PM10)","PM2.5":"29","PM10":"55","CO":"0.833","NO2":"21","O3":"59","O3_8h":"39","SO2":"6"},"安康":{"city":"安康","AQI":"54","quality":"良","pollutant":"颗粒物(PM10)","PM2.5":"34","PM10":"56","CO":"0.667","NO2":"8","O3":"145","O3_8h":"77","SO2":"10"},"唐山":{"city":"唐山","AQI":"54","quality":"良","pollutant":"颗粒物(PM10)","PM2.5":"19","PM10":"56","CO":"1.45","NO2":"32","O3":"51","O3_8h":"30","SO2":"46"},"漳州":{"city":"漳州","AQI":"54","quality":"良","pollutant":"颗粒物(PM10)","PM2.5":"31","PM10":"55","CO":"0.7","NO2":"27","O3":"66","O3_8h":"41","SO2":"4"},"江门":{"city":"江门","AQI":"54","quality":"良","pollutant":"颗粒物(PM10)","PM2.5":"22","PM10":"56","CO":"0.525","NO2":"5","O3":"92","O3_8h":"62","SO2":"5"},"海北州":{"city":"海北州","AQI":"55","quality":"良","pollutant":"臭氧8小时颗粒物(PM10)颗粒物(PM2.5)","PM2.5":"38","PM10":"58","CO":"0.7","NO2":"6","O3":"123","O3_8h":"104","SO2":"14"},"湘西州":{"city":"湘西州","AQI":"55","quality":"良","pollutant":"颗粒物(PM10)","PM2.5":"18","PM10":"58","CO":"0.867","NO2":"7","O3":"105","O3_8h":"48","SO2":"3"},"广州":{"city":"广州","AQI":"55","quality":"良","pollutant":"颗粒物(PM10)","PM2.5":"28","PM10":"57","CO":"0.673","NO2":"24","O3":"129","O3_8h":"60","SO2":"9"},"防城港":{"city":"防城港","AQI":"55","quality":"良","pollutant":"颗粒物(PM10)","PM2.5":"27","PM10":"58","CO":"0.6","NO2":"14","O3":"90","O3_8h":"60","SO2":"16"},"日喀则地区":{"city":"日喀则地区","AQI":"56","quality":"良","pollutant":"臭氧8小时","PM2.5":"8","PM10":"26","CO":"0.45","NO2":"5","O3":"119","O3_8h":"105","SO2":"17"},"日照":{"city":"日照","AQI":"56","quality":"良","pollutant":"臭氧8小时","PM2.5":"14","PM10":"58","CO":"0.3","NO2":"14","O3":"129","O3_8h":"106","SO2":"11"},"揭阳":{"city":"揭阳","AQI":"56","quality":"良","pollutant":"颗粒物(PM10)","PM2.5":"19","PM10":"60","CO":"0.633","NO2":"10","O3":"62","O3_8h":"52","SO2":"7"},"汉中":{"city":"汉中","AQI":"56","quality":"良","pollutant":"颗粒物(PM2.5)","PM2.5":"39","PM10":"58","CO":"0.75","NO2":"8","O3":"145","O3_8h":"75","SO2":"9"},"成都":{"city":"成都","AQI":"56","quality":"良","pollutant":"颗粒物(PM10)","PM2.5":"38","PM10":"59","CO":"0.5","NO2":"18","O3":"129","O3_8h":"66","SO2":"10"},"东莞":{"city":"东莞","AQI":"56","quality":"良","pollutant":"颗粒物(PM2.5)","PM2.5":"39","PM10":"50","CO":"0.65","NO2":"18","O3":"138","O3_8h":"73","SO2":"10"},"梧州":{"city":"梧州","AQI":"56","quality":"良","pollutant":"颗粒物(PM10)","PM2.5":"29","PM10":"60","CO":"0.975","NO2":"12","O3":"107","O3_8h":"47","SO2":"10"},"宜宾":{"city":"宜宾","AQI":"56","quality":"良","pollutant":"颗粒物(PM10)","PM2.5":"36","PM10":"59","CO":"0.9","NO2":"11","O3":"125","O3_8h":"60","SO2":"18"},"衢州":{"city":"衢州","AQI":"56","quality":"良","pollutant":"颗粒物(PM2.5)","PM2.5":"39","PM10":"57","CO":"0.533","NO2":"10","O3":"150","O3_8h":"85","SO2":"5"},"北京":{"city":"北京","AQI":"56","quality":"良","pollutant":"颗粒物(PM10)","PM2.5":"21","PM10":"60","CO":"0.855","NO2":"23","O3":"76","O3_8h":"47","SO2":"12"},"湘潭":{"city":"湘潭","AQI":"57","quality":"良","pollutant":"颗粒物(PM10)","PM2.5":"35","PM10":"61","CO":"0.8","NO2":"12","O3":"146","O3_8h":"76","SO2":"10"},"莱州":{"city":"莱州","AQI":"57","quality":"良","pollutant":"颗粒物(PM10)","PM2.5":"13","PM10":"62","CO":"0.5","NO2":"16","O3":"151","O3_8h":"105","SO2":"21"},"广安":{"city":"广安","AQI":"57","quality":"良","pollutant":"颗粒物(PM10)","PM2.5":"29","PM10":"61","CO":"0.52","NO2":"7","O3":"127","O3_8h":"77","SO2":"13"},"山南地区":{"city":"山南地区","AQI":"58","quality":"良","pollutant":"臭氧8小时","PM2.5":"3","PM10":"13","CO":"0.5","NO2":"1","O3":"134","O3_8h":"108","SO2":"5"},"乌兰察布":{"city":"乌兰察布","AQI":"58","quality":"良","pollutant":"臭氧8小时","PM2.5":"33","PM10":"57","CO":"0.35","NO2":"6","O3":"128","O3_8h":"108","SO2":"15"},"海南州":{"city":"海南州","AQI":"58","quality":"良","pollutant":"臭氧8小时","PM2.5":"29","PM10":"45","CO":"0.6","NO2":"11","O3":"120","O3_8h":"108","SO2":"23"},"娄底":{"city":"娄底","AQI":"58","quality":"良","pollutant":"颗粒物(PM10)","PM2.5":"35","PM10":"63","CO":"1.72","NO2":"18","O3":"121","O3_8h":"64","SO2":"19"},"保山":{"city":"保山","AQI":"58","quality":"良","pollutant":"颗粒物(PM10)","PM2.5":"13","PM10":"64","CO":"0.7","NO2":"2","O3":"117","O3_8h":"90","SO2":"8"},"即墨":{"city":"即墨","AQI":"58","quality":"良","pollutant":"臭氧8小时","PM2.5":"7","PM10":"44","CO":"0.15","NO2":"7","O3":"117","O3_8h":"108","SO2":"2"},"新余":{"city":"新余","AQI":"58","quality":"良","pollutant":"颗粒物(PM2.5)","PM2.5":"40","PM10":"55","CO":"0.76","NO2":"7","O3":"134","O3_8h":"83","SO2":"16"},"烟台":{"city":"烟台","AQI":"58","quality":"良","pollutant":"颗粒物(PM10)","PM2.5":"8","PM10":"64","CO":"0.383","NO2":"19","O3":"81","O3_8h":"61","SO2":"10"},"五家渠":{"city":"五家渠","AQI":"59","quality":"良","pollutant":"颗粒物(PM10)","PM2.5":"6","PM10":"65","CO":"0.7","NO2":"15","O3":"77","O3_8h":"35","SO2":"8"},"怀化":{"city":"怀化","AQI":"59","quality":"良","pollutant":"颗粒物(PM10)","PM2.5":"32","PM10":"66","CO":"0.94","NO2":"8","O3":"130","O3_8h":"69","SO2":"4"},"黔西南州":{"city":"黔西南州","AQI":"59","quality":"良","pollutant":"颗粒物(PM10)","PM2.5":"27","PM10":"66","CO":"0.55","NO2":"8","O3":"86","O3_8h":"66","SO2":"2"},"黄山":{"city":"黄山","AQI":"59","quality":"良","pollutant":"颗粒物(PM2.5)颗粒物(PM10)","PM2.5":"41","PM10":"65","CO":"0.667","NO2":"11","O3":"143","O3_8h":"101","SO2":"13"},"重庆":{"city":"重庆","AQI":"60","quality":"良","pollutant":"颗粒物(PM10)","PM2.5":"38","PM10":"68","CO":"0.675","NO2":"24","O3":"134","O3_8h":"56","SO2":"11"},"吉安":{"city":"吉安","AQI":"60","quality":"良","pollutant":"颗粒物(PM2.5)","PM2.5":"42","PM10":"55","CO":"0.65","NO2":"4","O3":"85","O3_8h":"68","SO2":"19"},"长沙":{"city":"长沙","AQI":"60","quality":"良","pollutant":"颗粒物(PM2.5)","PM2.5":"42","PM10":"57","CO":"0.73","NO2":"15","O3":"155","O3_8h":"84","SO2":"6"},"九江":{"city":"九江","AQI":"60","quality":"良","pollutant":"颗粒物(PM10)","PM2.5":"41","PM10":"67","CO":"0.663","NO2":"12","O3":"162","O3_8h":"98","SO2":"20"},"遂宁":{"city":"遂宁","AQI":"61","quality":"良","pollutant":"颗粒物(PM2.5)","PM2.5":"43","PM10":"67","CO":"0.45","NO2":"9","O3":"142","O3_8h":"77","SO2":"12"},"胶州":{"city":"胶州","AQI":"61","quality":"良","pollutant":"颗粒物(PM10)","PM2.5":"7","PM10":"69","CO":"0.35","NO2":"16","O3":"128","O3_8h":"106","SO2":"8"},"内江":{"city":"内江","AQI":"61","quality":"良","pollutant":"颗粒物(PM2.5)","PM2.5":"43","PM10":"46","CO":"0.35","NO2":"19","O3":"145","O3_8h":"76","SO2":"16"},"遵义":{"city":"遵义","AQI":"61","quality":"良","pollutant":"颗粒物(PM10)","PM2.5":"22","PM10":"69","CO":"0.45","NO2":"13","O3":"99","O3_8h":"37","SO2":"4"},"乌海":{"city":"乌海","AQI":"61","quality":"良","pollutant":"颗粒物(PM10)","PM2.5":"16","PM10":"70","CO":"0.4","NO2":"7","O3":"111","O3_8h":"108","SO2":"7"},"张家界":{"city":"张家界","AQI":"61","quality":"良","pollutant":"颗粒物(PM10)","PM2.5":"34","PM10":"69","CO":"0.975","NO2":"7","O3":"148","O3_8h":"90","SO2":"9"},"铜仁地区":{"city":"铜仁地区","AQI":"61","quality":"良","pollutant":"颗粒物(PM10)","PM2.5":"12","PM10":"69","CO":"0.5","NO2":"39","O3":"62","O3_8h":"23","SO2":"15"},"临夏州":{"city":"临夏州","AQI":"62","quality":"良","pollutant":"颗粒物(PM10)","PM2.5":"24","PM10":"72","CO":"0.75","NO2":"19","O3":"54","O3_8h":"32","SO2":"21"},"钦州":{"city":"钦州","AQI":"62","quality":"良","pollutant":"颗粒物(PM10)","PM2.5":"33","PM10":"71","CO":"0.667","NO2":"8","O3":"109","O3_8h":"71","SO2":"11"},"阿克苏地区":{"city":"阿克苏地区","AQI":"62","quality":"良","pollutant":"颗粒物(PM10)","PM2.5":"36","PM10":"72","CO":"0.7","NO2":"6","O3":"108","O3_8h":"81","SO2":"7"},"常州":{"city":"常州","AQI":"62","quality":"良","pollutant":"臭氧8小时","PM2.5":"37","PM10":"56","CO":"0.933","NO2":"30","O3":"163","O3_8h":"113","SO2":"14"},"绵阳":{"city":"绵阳","AQI":"63","quality":"良","pollutant":"颗粒物(PM2.5)","PM2.5":"44","PM10":"65","CO":"0.6","NO2":"13","O3":"142","O3_8h":"78","SO2":"5"},"盐城":{"city":"盐城","AQI":"63","quality":"良","pollutant":"颗粒物(PM10)","PM2.5":"17","PM10":"74","CO":"0.54","NO2":"11","O3":"129","O3_8h":"110","SO2":"9"},"六盘水":{"city":"六盘水","AQI":"63","quality":"良","pollutant":"颗粒物(PM10)","PM2.5":"39","PM10":"74","CO":"0.54","NO2":"14","O3":"84","O3_8h":"61","SO2":"13"},"拉萨":{"city":"拉萨","AQI":"64","quality":"良","pollutant":"臭氧8小时","PM2.5":"10","PM10":"24","CO":"0.56","NO2":"7","O3":"129","O3_8h":"115","SO2":"9"},"上饶":{"city":"上饶","AQI":"64","quality":"良","pollutant":"颗粒物(PM2.5)","PM2.5":"45","PM10":"62","CO":"0.875","NO2":"6","O3":"112","O3_8h":"77","SO2":"4"},"迪庆州":{"city":"迪庆州","AQI":"65","quality":"良","pollutant":"臭氧8小时","PM2.5":"3","PM10":"38","CO":"1.0","NO2":"8","O3":"123","O3_8h":"116","SO2":"16"},"景德镇":{"city":"景德镇","AQI":"66","quality":"良","pollutant":"颗粒物(PM2.5)","PM2.5":"47","PM10":"60","CO":"1.06","NO2":"3","O3":"128","O3_8h":"72","SO2":"4"},"临沂":{"city":"临沂","AQI":"66","quality":"良","pollutant":"臭氧8小时","PM2.5":"19","PM10":"74","CO":"0.625","NO2":"13","O3":"164","O3_8h":"118","SO2":"13"},"恩施州":{"city":"恩施州","AQI":"66","quality":"良","pollutant":"颗粒物(PM2.5)","PM2.5":"47","PM10":"71","CO":"0.85","NO2":"11","O3":"103","O3_8h":"47","SO2":"12"},"寿光":{"city":"寿光","AQI":"66","quality":"良","pollutant":"臭氧8小时","PM2.5":"11","PM10":"72","CO":"0.55","NO2":"9","O3":"167","O3_8h":"118","SO2":"6"},"莱芜":{"city":"莱芜","AQI":"66","quality":"良","pollutant":"颗粒物(PM10)","PM2.5":"30","PM10":"79","CO":"0.45","NO2":"19","O3":"162","O3_8h":"107","SO2":"21"},"商洛":{"city":"商洛","AQI":"67","quality":"良","pollutant":"臭氧1小时","PM2.5":"43","PM10":"66","CO":"0.7","NO2":"9","O3":"172","O3_8h":"114","SO2":"24"},"胶南":{"city":"胶南","AQI":"68","quality":"良","pollutant":"臭氧8小时","PM2.5":"11","PM10":"50","CO":"0.35","NO2":"9","O3":"137","O3_8h":"120","SO2":"6"},"吕梁":{"city":"吕梁","AQI":"68","quality":"良","pollutant":"臭氧1小时","PM2.5":"40","PM10":"78","CO":"1.033","NO2":"22","O3":"173","O3_8h":"118","SO2":"12"},"广元":{"city":"广元","AQI":"68","quality":"良","pollutant":"颗粒物(PM10)","PM2.5":"45","PM10":"83","CO":"0.65","NO2":"18","O3":"125","O3_8h":"52","SO2":"30"},"滨州":{"city":"滨州","AQI":"69","quality":"良","pollutant":"臭氧1小时","PM2.5":"32","PM10":"61","CO":"0.9","NO2":"21","O3":"174","O3_8h":"118","SO2":"19"},"西宁":{"city":"西宁","AQI":"69","quality":"良","pollutant":"颗粒物(PM10)","PM2.5":"48","PM10":"85","CO":"1.1","NO2":"35","O3":"92","O3_8h":"47","SO2":"13"},"资阳":{"city":"资阳","AQI":"69","quality":"良","pollutant":"颗粒物(PM10)","PM2.5":"36","PM10":"86","CO":"0.48","NO2":"13","O3":"130","O3_8h":"77","SO2":"9"},"淮安":{"city":"淮安","AQI":"70","quality":"良","pollutant":"臭氧8小时","PM2.5":"9","PM10":"63","CO":"0.24","NO2":"11","O3":"156","O3_8h":"122","SO2":"8"},"富阳":{"city":"富阳","AQI":"70","quality":"良","pollutant":"颗粒物(PM2.5)","PM2.5":"50","PM10":"56","CO":"0.7","NO2":"8","O3":"133","O3_8h":"85","SO2":"11"},"常德":{"city":"常德","AQI":"70","quality":"良","pollutant":"臭氧1小时","PM2.5":"23","PM10":"47","CO":"0.9","NO2":"4","O3":"175","O3_8h":"91","SO2":"7"},"金华":{"city":"金华","AQI":"70","quality":"良","pollutant":"臭氧1小时","PM2.5":"43","PM10":"61","CO":"0.6","NO2":"11","O3":"175","O3_8h":"102","SO2":"3"},"舟山":{"city":"舟山","AQI":"71","quality":"良","pollutant":"臭氧8小时","PM2.5":"41","PM10":"66","CO":"0.833","NO2":"4","O3":"163","O3_8h":"124","SO2":"6"},"潍坊":{"city":"潍坊","AQI":"71","quality":"良","pollutant":"颗粒物(PM10)","PM2.5":"17","PM10":"89","CO":"0.3","NO2":"9","O3":"160","O3_8h":"122","SO2":"10"},"固原":{"city":"固原","AQI":"71","quality":"良","pollutant":"臭氧8小时","PM2.5":"20","PM10":"80","CO":"0.867","NO2":"8","O3":"157","O3_8h":"123","SO2":"7"},"荆门":{"city":"荆门","AQI":"72","quality":"良","pollutant":"颗粒物(PM2.5)","PM2.5":"52","PM10":"89","CO":"0.88","NO2":"23","O3":"126","O3_8h":"78","SO2":"11"},"自贡":{"city":"自贡","AQI":"72","quality":"良","pollutant":"颗粒物(PM2.5)","PM2.5":"52","PM10":"72","CO":"0.625","NO2":"18","O3":"133","O3_8h":"67","SO2":"12"},"乐山":{"city":"乐山","AQI":"72","quality":"良","pollutant":"臭氧1小时","PM2.5":"36","PM10":"53","CO":"0.525","NO2":"11","O3":"176","O3_8h":"67","SO2":"25"},"岳阳":{"city":"岳阳","AQI":"72","quality":"良","pollutant":"颗粒物(PM2.5)","PM2.5":"52","PM10":"65","CO":"0.78","NO2":"6","O3":"163","O3_8h":"89","SO2":"14"},"甘南州":{"city":"甘南州","AQI":"73","quality":"良","pollutant":"颗粒物(PM10)","PM2.5":"46","PM10":"93","CO":"0.9","NO2":"5","O3":"116","O3_8h":"70","SO2":"6"},"白银":{"city":"白银","AQI":"74","quality":"良","pollutant":"颗粒物(PM10)","PM2.5":"32","PM10":"95","CO":"0.75","NO2":"11","O3":"111","O3_8h":"101","SO2":"12"},"天水":{"city":"天水","AQI":"74","quality":"良","pollutant":"颗粒物(PM10)","PM2.5":"18","PM10":"95","CO":"0.3","NO2":"5","O3":"139","O3_8h":"112","SO2":"10"},"杭州":{"city":"杭州","AQI":"75","quality":"良","pollutant":"臭氧8小时","PM2.5":"43","PM10":"61","CO":"0.9","NO2":"15","O3":"178","O3_8h":"128","SO2":"8"},"克州":{"city":"克州","AQI":"75","quality":"良","pollutant":"臭氧8小时","PM2.5":"49","PM10":"65","CO":"1.2","NO2":"7","O3":"146","O3_8h":"128","SO2":"3"},"贵阳":{"city":"贵阳","AQI":"75","quality":"良","pollutant":"臭氧1小时","PM2.5":"35","PM10":"61","CO":"0.63","NO2":"20","O3":"179","O3_8h":"109","SO2":"11"},"常熟":{"city":"常熟","AQI":"76","quality":"良","pollutant":"臭氧8小时","PM2.5":"19","PM10":"55","CO":"0.4","NO2":"16","O3":"145","O3_8h":"130","SO2":"15"},"黄南州":{"city":"黄南州","AQI":"76","quality":"良","pollutant":"颗粒物(PM2.5)","PM2.5":"55","PM10":"88","CO":"1.3","NO2":"18","O3":"84","O3_8h":"54","SO2":"10"},"咸宁":{"city":"咸宁","AQI":"76","quality":"良","pollutant":"颗粒物(PM2.5)","PM2.5":"55","PM10":"58","CO":"1.25","NO2":"3","O3":"140","O3_8h":"98","SO2":"4"},"张家口":{"city":"张家口","AQI":"76","quality":"良","pollutant":"颗粒物(PM10)","PM2.5":"29","PM10":"100","CO":"0.4","NO2":"18","O3":"120","O3_8h":"127","SO2":"14"},"绍兴":{"city":"绍兴","AQI":"76","quality":"良","pollutant":"颗粒物(PM10)","PM2.5":"43","PM10":"99","CO":"0.742","NO2":"9","O3":"141","O3_8h":"101","SO2":"9"},"海东地区":{"city":"海东地区","AQI":"77","quality":"良","pollutant":"颗粒物(PM10)","PM2.5":"47","PM10":"102","CO":"1.1","NO2":"33","O3":"102","O3_8h":"40","SO2":"21"},"张家港":{"city":"张家港","AQI":"78","quality":"良","pollutant":"臭氧8小时","PM2.5":"15","PM10":"66","CO":"0.7","NO2":"24","O3":"149","O3_8h":"132","SO2":"15"},"临安":{"city":"临安","AQI":"78","quality":"良","pollutant":"颗粒物(PM2.5)","PM2.5":"57","PM10":"95","CO":"0.65","NO2":"14","O3":"101","O3_8h":"64","SO2":"15"},"宁波":{"city":"宁波","AQI":"78","quality":"良","pollutant":"颗粒物(PM2.5)","PM2.5":"57","PM10":"79","CO":"0.788","NO2":"26","O3":"174","O3_8h":"101","SO2":"13"},"南充":{"city":"南充","AQI":"78","quality":"良","pollutant":"颗粒物(PM2.5)","PM2.5":"57","PM10":"102","CO":"0.567","NO2":"15","O3":"157","O3_8h":"88","SO2":"11"},"东营":{"city":"东营","AQI":"79","quality":"良","pollutant":"颗粒物(PM10)","PM2.5":"26","PM10":"106","CO":"0.65","NO2":"19","O3":"148","O3_8h":"124","SO2":"23"},"保定":{"city":"保定","AQI":"79","quality":"良","pollutant":"颗粒物(PM10)","PM2.5":"38","PM10":"105","CO":"1.6","NO2":"49","O3":"88","O3_8h":"63","SO2":"26"},"十堰":{"city":"十堰","AQI":"79","quality":"良","pollutant":"臭氧1小时","PM2.5":"46","PM10":"74","CO":"0.75","NO2":"11","O3":"182","O3_8h":"119","SO2":"12"},"庆阳":{"city":"庆阳","AQI":"79","quality":"良","pollutant":"臭氧8小时","PM2.5":"17","PM10":"27","CO":"0.5","NO2":"8","O3":"149","O3_8h":"133","SO2":"4"},"平度":{"city":"平度","AQI":"79","quality":"良","pollutant":"颗粒物(PM10)","PM2.5":"12","PM10":"105","CO":"0.3","NO2":"6","O3":"122","O3_8h":"104","SO2":"4"},"兰州":{"city":"兰州","AQI":"79","quality":"良","pollutant":"颗粒物(PM10)","PM2.5":"44","PM10":"106","CO":"0.66","NO2":"32","O3":"124","O3_8h":"90","SO2":"7"},"淄博":{"city":"淄博","AQI":"79","quality":"良","pollutant":"臭氧1小时","PM2.5":"27","PM10":"94","CO":"1.0","NO2":"18","O3":"182","O3_8h":"130","SO2":"18"},"巴彦淖尔":{"city":"巴彦淖尔","AQI":"81","quality":"良","pollutant":"颗粒物(PM10)","PM2.5":"35","PM10":"110","CO":"0.233","NO2":"9","O3":"93","O3_8h":"80","SO2":"3"},"南通":{"city":"南通","AQI":"81","quality":"良","pollutant":"臭氧8小时","PM2.5":"12","PM10":"33","CO":"0.42","NO2":"11","O3":"145","O3_8h":"135","SO2":"19"},"溧阳":{"city":"溧阳","AQI":"82","quality":"良","pollutant":"颗粒物(PM2.5)","PM2.5":"60","PM10":"74","CO":"1.05","NO2":"11","O3":"157","O3_8h":"120","SO2":"7"},"宿迁":{"city":"宿迁","AQI":"83","quality":"良","pollutant":"臭氧1小时","PM2.5":"26","PM10":"94","CO":"0.425","NO2":"12","O3":"185","O3_8h":"130","SO2":"9"},"天津":{"city":"天津","AQI":"83","quality":"良","pollutant":"颗粒物(PM10)","PM2.5":"21","PM10":"113","CO":"0.835","NO2":"32","O3":"54","O3_8h":"54","SO2":"14"},"安庆":{"city":"安庆","AQI":"85","quality":"良","pollutant":"颗粒物(PM2.5)","PM2.5":"62","PM10":"96","CO":"0.825","NO2":"11","O3":"173","O3_8h":"101","SO2":"9"},"宝鸡":{"city":"宝鸡","AQI":"85","quality":"良","pollutant":"臭氧1小时","PM2.5":"31","PM10":"61","CO":"0.488","NO2":"12","O3":"187","O3_8h":"115","SO2":"7"},"德阳":{"city":"德阳","AQI":"85","quality":"良","pollutant":"臭氧1小时","PM2.5":"41","PM10":"76","CO":"0.625","NO2":"16","O3":"187","O3_8h":"94","SO2":"14"},"信阳":{"city":"信阳","AQI":"85","quality":"良","pollutant":"臭氧1小时","PM2.5":"42","PM10":"71","CO":"0.65","NO2":"6","O3":"187","O3_8h":"127","SO2":"9"},"上海":{"city":"上海","AQI":"86","quality":"良","pollutant":"臭氧8小时","PM2.5":"16","PM10":"36","CO":"0.39","NO2":"22","O3":"135","O3_8h":"142","SO2":"8"},"那曲地区":{"city":"那曲地区","AQI":"86","quality":"良","pollutant":"颗粒物(PM10)","PM2.5":"25","PM10":"120","CO":"0.7","NO2":"9","O3":"72","O3_8h":"67","SO2":"4"},"太仓":{"city":"太仓","AQI":"86","quality":"良","pollutant":"臭氧8小时","PM2.5":"20","PM10":"51","CO":"0.95","NO2":"24","O3":"140","O3_8h":"141","SO2":"13"},"江阴":{"city":"江阴","AQI":"87","quality":"良","pollutant":"臭氧1小时","PM2.5":"33","PM10":"62","CO":"0.4","NO2":"18","O3":"188","O3_8h":"136","SO2":"14"},"黄石":{"city":"黄石","AQI":"88","quality":"良","pollutant":"颗粒物(PM2.5)","PM2.5":"65","PM10":"100","CO":"0.925","NO2":"8","O3":"178","O3_8h":"100","SO2":"9"},"达州":{"city":"达州","AQI":"88","quality":"良","pollutant":"颗粒物(PM2.5)","PM2.5":"65","PM10":"109","CO":"1.06","NO2":"21","O3":"132","O3_8h":"71","SO2":"15"},"大同":{"city":"大同","AQI":"88","quality":"良","pollutant":"颗粒物(PM10)","PM2.5":"29","PM10":"124","CO":"0.717","NO2":"5","O3":"115","O3_8h":"93","SO2":"9"},"泰州":{"city":"泰州","AQI":"88","quality":"良","pollutant":"臭氧8小时","PM2.5":"14","PM10":"65","CO":"0.55","NO2":"16","O3":"170","O3_8h":"144","SO2":"9"},"石家庄":{"city":"石家庄","AQI":"89","quality":"良","pollutant":"颗粒物(PM10)","PM2.5":"50","PM10":"126","CO":"0.95","NO2":"27","O3":"179","O3_8h":"101","SO2":"46"},"玉树州":{"city":"玉树州","AQI":"89","quality":"良","pollutant":"臭氧8小时","PM2.5":"7","PM10":"12","CO":"0.3","NO2":"6","O3":"148","O3_8h":"145","SO2":"4"},"章丘":{"city":"章丘","AQI":"90","quality":"良","pollutant":"臭氧1小时","PM2.5":"30","PM10":"94","CO":"0.4","NO2":"12","O3":"191","O3_8h":"142","SO2":"21"},"沧州":{"city":"沧州","AQI":"90","quality":"良","pollutant":"颗粒物(PM10)","PM2.5":"33","PM10":"127","CO":"0.3","NO2":"27","O3":"108","O3_8h":"90","SO2":"21"},"济南":{"city":"济南","AQI":"94","quality":"良","pollutant":"臭氧1小时","PM2.5":"46","PM10":"122","CO":"0.8","NO2":"18","O3":"194","O3_8h":"147","SO2":"45"},"朔州":{"city":"朔州","AQI":"96","quality":"良","pollutant":"臭氧8小时","PM2.5":"33","PM10":"89","CO":"0.52","NO2":"8","O3":"144","O3_8h":"154","SO2":"10"},"鄂尔多斯":{"city":"鄂尔多斯","AQI":"96","quality":"良","pollutant":"颗粒物(PM10)","PM2.5":"30","PM10":"140","CO":"0.56","NO2":"10","O3":"123","O3_8h":"106","SO2":"7"},"武汉":{"city":"武汉","AQI":"97","quality":"良","pollutant":"臭氧1小时","PM2.5":"56","PM10":"104","CO":"1.21","NO2":"21","O3":"196","O3_8h":"84","SO2":"7"},"宜昌":{"city":"宜昌","AQI":"99","quality":"良","pollutant":"臭氧1小时","PM2.5":"37","PM10":"79","CO":"0.98","NO2":"20","O3":"198","O3_8h":"115","SO2":"14"},"昆山":{"city":"昆山","AQI":"99","quality":"良","pollutant":"臭氧8小时","PM2.5":"20","PM10":"50","CO":"0.45","NO2":"24","O3":"161","O3_8h":"157","SO2":"12"},"六安":{"city":"六安","AQI":"99","quality":"良","pollutant":"颗粒物(PM2.5)","PM2.5":"74","PM10":"108","CO":"0.925","NO2":"28","O3":"195","O3_8h":"152","SO2":"11"},"阜阳":{"city":"阜阳","AQI":"99","quality":"良","pollutant":"臭氧1小时","PM2.5":"72","PM10":"136","CO":"0.7","NO2":"12","O3":"198","O3_8h":"132","SO2":"8"},"枣庄":{"city":"枣庄","AQI":"100","quality":"良","pollutant":"臭氧1小时","PM2.5":"37","PM10":"115","CO":"0.38","NO2":"10","O3":"199","O3_8h":"136","SO2":"33"},"阿里地区":{"city":"阿里地区","AQI":"101","quality":"轻度污染","pollutant":"臭氧8小时","PM2.5":"8","PM10":"30","CO":"0.35","NO2":"3","O3":"167","O3_8h":"160","SO2":"6"},"鄂州":{"city":"鄂州","AQI":"101","quality":"轻度污染","pollutant":"臭氧1小时","PM2.5":"64","PM10":"90","CO":"1.433","NO2":"13","O3":"200","O3_8h":"104","SO2":"11"},"张掖":{"city":"张掖","AQI":"101","quality":"轻度污染","pollutant":"颗粒物(PM10)","PM2.5":"27","PM10":"150","CO":"0.15","NO2":"7","O3":"112","O3_8h":"61","SO2":"7"},"孝感":{"city":"孝感","AQI":"103","quality":"轻度污染","pollutant":"臭氧1小时","PM2.5":"48","PM10":"88","CO":"0.8","NO2":"14","O3":"204","O3_8h":"116","SO2":"6"},"荆州":{"city":"荆州","AQI":"104","quality":"轻度污染","pollutant":"颗粒物(PM2.5)","PM2.5":"77","PM10":"129","CO":"0.833","NO2":"14","O3":"175","O3_8h":"83","SO2":"17"},"黄冈":{"city":"黄冈","AQI":"104","quality":"轻度污染","pollutant":"臭氧1小时","PM2.5":"50","PM10":"78","CO":"1.65","NO2":"7","O3":"205","O3_8h":"120","SO2":"5"},"襄阳":{"city":"襄阳","AQI":"105","quality":"轻度污染","pollutant":"臭氧1小时","PM2.5":"41","PM10":"88","CO":"0.9","NO2":"11","O3":"207","O3_8h":"125","SO2":"14"},"榆林":{"city":"榆林","AQI":"105","quality":"轻度污染","pollutant":"臭氧1小时","PM2.5":"33","PM10":"80","CO":"0.9","NO2":"12","O3":"207","O3_8h":"146","SO2":"8"},"石嘴山":{"city":"石嘴山","AQI":"105","quality":"轻度污染","pollutant":"颗粒物(PM10)","PM2.5":"24","PM10":"158","CO":"0.4","NO2":"13","O3":"114","O3_8h":"91","SO2":"33"},"忻州":{"city":"忻州","AQI":"106","quality":"轻度污染","pollutant":"臭氧1小时","PM2.5":"51","PM10":"126","CO":"1.7","NO2":"43","O3":"210","O3_8h":"147","SO2":"20"},"宜兴":{"city":"宜兴","AQI":"107","quality":"轻度污染","pollutant":"臭氧1小时","PM2.5":"64","PM10":"130","CO":"1.1","NO2":"10","O3":"212","O3_8h":"164","SO2":"7"},"铜川":{"city":"铜川","AQI":"107","quality":"轻度污染","pollutant":"臭氧1小时","PM2.5":"31","PM10":"63","CO":"1.175","NO2":"8","O3":"211","O3_8h":"157","SO2":"18"},"蚌埠":{"city":"蚌埠","AQI":"107","quality":"轻度污染","pollutant":"臭氧1小时","PM2.5":"68","PM10":"125","CO":"0.8","NO2":"14","O3":"212","O3_8h":"141","SO2":"16"},"随州":{"city":"随州","AQI":"108","quality":"轻度污染","pollutant":"臭氧1小时","PM2.5":"61","PM10":"99","CO":"1.1","NO2":"8","O3":"214","O3_8h":"129","SO2":"6"},"泰安":{"city":"泰安","AQI":"109","quality":"轻度污染","pollutant":"臭氧1小时","PM2.5":"28","PM10":"69","CO":"0.433","NO2":"11","O3":"216","O3_8h":"158","SO2":"14"},"湖州":{"city":"湖州","AQI":"110","quality":"轻度污染","pollutant":"颗粒物(PM2.5)","PM2.5":"82","PM10":"107","CO":"0.994","NO2":"41","O3":"153","O3_8h":"103","SO2":"15"},"徐州":{"city":"徐州","AQI":"110","quality":"轻度污染","pollutant":"颗粒物(PM10)","PM2.5":"50","PM10":"167","CO":"0.629","NO2":"9","O3":"216","O3_8h":"150","SO2":"14"},"池州":{"city":"池州","AQI":"110","quality":"轻度污染","pollutant":"颗粒物(PM2.5)","PM2.5":"82","PM10":"114","CO":"0.667","NO2":"11","O3":"182","O3_8h":"122","SO2":"6"},"衡水":{"city":"衡水","AQI":"110","quality":"轻度污染","pollutant":"颗粒物(PM10)","PM2.5":"50","PM10":"168","CO":"0.733","NO2":"19","O3":"216","O3_8h":"137","SO2":"19"},"喀什地区":{"city":"喀什地区","AQI":"111","quality":"轻度污染","pollutant":"颗粒物(PM10)","PM2.5":"56","PM10":"169","CO":"0.7","NO2":"83","O3":"104","O3_8h":"67","SO2":"16"},"亳州":{"city":"亳州","AQI":"112","quality":"轻度污染","pollutant":"臭氧1小时","PM2.5":"59","PM10":"135","CO":"0.8","NO2":"8","O3":"222","O3_8h":"149","SO2":"10"},"扬州":{"city":"扬州","AQI":"112","quality":"轻度污染","pollutant":"臭氧1小时","PM2.5":"37","PM10":"93","CO":"0.775","NO2":"13","O3":"221","O3_8h":"153","SO2":"15"},"太原":{"city":"太原","AQI":"112","quality":"轻度污染","pollutant":"臭氧1小时","PM2.5":"48","PM10":"117","CO":"0.925","NO2":"17","O3":"221","O3_8h":"161","SO2":"32"},"德州":{"city":"德州","AQI":"113","quality":"轻度污染","pollutant":"臭氧1小时","PM2.5":"48","PM10":"163","CO":"1.033","NO2":"14","O3":"223","O3_8h":"133","SO2":"21"},"商丘":{"city":"商丘","AQI":"113","quality":"轻度污染","pollutant":"臭氧1小时","PM2.5":"59","PM10":"146","CO":"0.5","NO2":"11","O3":"223","O3_8h":"155","SO2":"10"},"晋中":{"city":"晋中","AQI":"113","quality":"轻度污染","pollutant":"臭氧8小时","PM2.5":"43","PM10":"105","CO":"0.975","NO2":"15","O3":"213","O3_8h":"173","SO2":"30"},"济宁":{"city":"济宁","AQI":"113","quality":"轻度污染","pollutant":"臭氧1小时","PM2.5":"38","PM10":"136","CO":"0.633","NO2":"12","O3":"223","O3_8h":"153","SO2":"18"},"嘉兴":{"city":"嘉兴","AQI":"113","quality":"轻度污染","pollutant":"臭氧1小时","PM2.5":"71","PM10":"101","CO":"1.067","NO2":"12","O3":"223","O3_8h":"139","SO2":"7"},"吴江":{"city":"吴江","AQI":"114","quality":"轻度污染","pollutant":"臭氧1小时","PM2.5":"49","PM10":"120","CO":"0.8","NO2":"20","O3":"225","O3_8h":"150","SO2":"15"},"金坛":{"city":"金坛","AQI":"114","quality":"轻度污染","pollutant":"臭氧1小时","PM2.5":"76","PM10":"99","CO":"0.8","NO2":"19","O3":"226","O3_8h":"146","SO2":"18"},"马鞍山":{"city":"马鞍山","AQI":"115","quality":"轻度污染","pollutant":"臭氧1小时","PM2.5":"74","PM10":"121","CO":"0.86","NO2":"10","O3":"228","O3_8h":"167","SO2":"6"},"晋城":{"city":"晋城","AQI":"116","quality":"轻度污染","pollutant":"臭氧8小时","PM2.5":"26","PM10":"55","CO":"0.633","NO2":"7","O3":"226","O3_8h":"176","SO2":"14"},"渭南":{"city":"渭南","AQI":"116","quality":"轻度污染","pollutant":"臭氧1小时","PM2.5":"54","PM10":"137","CO":"0.85","NO2":"9","O3":"230","O3_8h":"154","SO2":"10"},"咸阳":{"city":"咸阳","AQI":"116","quality":"轻度污染","pollutant":"臭氧1小时","PM2.5":"25","PM10":"65","CO":"1.025","NO2":"16","O3":"230","O3_8h":"156","SO2":"14"},"吴忠":{"city":"吴忠","AQI":"117","quality":"轻度污染","pollutant":"颗粒物(PM10)","PM2.5":"31","PM10":"182","CO":"0.633","NO2":"3","O3":"109","O3_8h":"85","SO2":"17"},"银川":{"city":"银川","AQI":"118","quality":"轻度污染","pollutant":"颗粒物(PM10)","PM2.5":"33","PM10":"183","CO":"0.343","NO2":"12","O3":"128","O3_8h":"105","SO2":"27"},"聊城":{"city":"聊城","AQI":"119","quality":"轻度污染","pollutant":"臭氧1小时","PM2.5":"39","PM10":"183","CO":"1.0","NO2":"13","O3":"236","O3_8h":"158","SO2":"12"},"苏州":{"city":"苏州","AQI":"119","quality":"轻度污染","pollutant":"臭氧1小时","PM2.5":"45","PM10":"83","CO":"0.675","NO2":"27","O3":"235","O3_8h":"164","SO2":"8"},"濮阳":{"city":"濮阳","AQI":"120","quality":"轻度污染","pollutant":"臭氧1小时","PM2.5":"53","PM10":"170","CO":"1.15","NO2":"18","O3":"238","O3_8h":"155","SO2":"14"},"宿州":{"city":"宿州","AQI":"120","quality":"轻度污染","pollutant":"臭氧1小时","PM2.5":"76","PM10":"133","CO":"0.7","NO2":"15","O3":"237","O3_8h":"156","SO2":"9"},"西安":{"city":"西安","AQI":"121","quality":"轻度污染","pollutant":"臭氧1小时","PM2.5":"37","PM10":"83","CO":"0.908","NO2":"18","O3":"240","O3_8h":"139","SO2":"10"},"无锡":{"city":"无锡","AQI":"121","quality":"轻度污染","pollutant":"臭氧1小时","PM2.5":"54","PM10":"94","CO":"0.95","NO2":"19","O3":"240","O3_8h":"177","SO2":"12"},"南京":{"city":"南京","AQI":"122","quality":"轻度污染","pollutant":"臭氧1小时","PM2.5":"87","PM10":"127","CO":"1.178","NO2":"21","O3":"242","O3_8h":"153","SO2":"15"},"漯河":{"city":"漯河","AQI":"122","quality":"轻度污染","pollutant":"臭氧1小时","PM2.5":"59","PM10":"178","CO":"0.775","NO2":"12","O3":"242","O3_8h":"162","SO2":"11"},"周口":{"city":"周口","AQI":"123","quality":"轻度污染","pollutant":"臭氧1小时","PM2.5":"59","PM10":"137","CO":"0.65","NO2":"13","O3":"243","O3_8h":"152","SO2":"6"},"淮南":{"city":"淮南","AQI":"123","quality":"轻度污染","pollutant":"臭氧1小时","PM2.5":"80","PM10":"139","CO":"1.0","NO2":"21","O3":"243","O3_8h":"174","SO2":"16"},"平顶山":{"city":"平顶山","AQI":"124","quality":"轻度污染","pollutant":"臭氧1小时","PM2.5":"60","PM10":"142","CO":"0.925","NO2":"16","O3":"245","O3_8h":"184","SO2":"12"},"镇江":{"city":"镇江","AQI":"124","quality":"轻度污染","pollutant":"臭氧1小时","PM2.5":"47","PM10":"97","CO":"0.975","NO2":"25","O3":"246","O3_8h":"149","SO2":"19"},"宣城":{"city":"宣城","AQI":"124","quality":"轻度污染","pollutant":"颗粒物(PM2.5)","PM2.5":"93","PM10":"131","CO":"0.7","NO2":"15","O3":"159","O3_8h":"115","SO2":"13"},"铜陵":{"city":"铜陵","AQI":"126","quality":"轻度污染","pollutant":"颗粒物(PM2.5)","PM2.5":"95","PM10":"117","CO":"1.017","NO2":"15","O3":"186","O3_8h":"125","SO2":"8"},"阳泉":{"city":"阳泉","AQI":"126","quality":"轻度污染","pollutant":"臭氧1小时","PM2.5":"65","PM10":"153","CO":"1.2","NO2":"27","O3":"250","O3_8h":"149","SO2":"29"},"阿拉善盟":{"city":"阿拉善盟","AQI":"126","quality":"轻度污染","pollutant":"颗粒物(PM10)","PM2.5":"59","PM10":"199","CO":"0.467","NO2":"7","O3":"166","O3_8h":"142","SO2":"25"},"淮北":{"city":"淮北","AQI":"128","quality":"轻度污染","pollutant":"臭氧1小时","PM2.5":"53","PM10":"167","CO":"0.933","NO2":"15","O3":"254","O3_8h":"168","SO2":"15"},"邯郸":{"city":"邯郸","AQI":"132","quality":"轻度污染","pollutant":"臭氧1小时","PM2.5":"68","PM10":"141","CO":"0.85","NO2":"18","O3":"262","O3_8h":"163","SO2":"16"},"吐鲁番地区":{"city":"吐鲁番地区","AQI":"132","quality":"轻度污染","pollutant":"颗粒物(PM2.5)","PM2.5":"100","PM10":"142","CO":"0.9","NO2":"21","O3":"75","O3_8h":"49","SO2":"12"},"洛阳":{"city":"洛阳","AQI":"133","quality":"轻度污染","pollutant":"臭氧1小时","PM2.5":"72","PM10":"153","CO":"0.986","NO2":"10","O3":"263","O3_8h":"179","SO2":"18"},"驻马店":{"city":"驻马店","AQI":"136","quality":"轻度污染","pollutant":"臭氧1小时","PM2.5":"48","PM10":"110","CO":"0.733","NO2":"9","O3":"269","O3_8h":"167","SO2":"14"},"南阳":{"city":"南阳","AQI":"136","quality":"轻度污染","pollutant":"臭氧8小时","PM2.5":"58","PM10":"125","CO":"0.86","NO2":"11","O3":"244","O3_8h":"198","SO2":"11"},"芜湖":{"city":"芜湖","AQI":"137","quality":"轻度污染","pollutant":"臭氧1小时","PM2.5":"77","PM10":"179","CO":"1.25","NO2":"14","O3":"271","O3_8h":"183","SO2":"9"},"滁州":{"city":"滁州","AQI":"138","quality":"轻度污染","pollutant":"臭氧1小时","PM2.5":"99","PM10":"148","CO":"1.367","NO2":"18","O3":"274","O3_8h":"162","SO2":"24"},"菏泽":{"city":"菏泽","AQI":"138","quality":"轻度污染","pollutant":"颗粒物(PM10)","PM2.5":"81","PM10":"223","CO":"1.3","NO2":"25","O3":"229","O3_8h":"155","SO2":"17"},"中卫":{"city":"中卫","AQI":"139","quality":"轻度污染","pollutant":"颗粒物(PM10)","PM2.5":"67","PM10":"225","CO":"0.567","NO2":"12","O3":"146","O3_8h":"101","SO2":"34"},"包头":{"city":"包头","AQI":"139","quality":"轻度污染","pollutant":"颗粒物(PM10)","PM2.5":"55","PM10":"225","CO":"0.35","NO2":"6","O3":"101","O3_8h":"90","SO2":"7"},"焦作":{"city":"焦作","AQI":"141","quality":"轻度污染","pollutant":"臭氧1小时","PM2.5":"58","PM10":"133","CO":"0.975","NO2":"27","O3":"279","O3_8h":"190","SO2":"26"},"合肥":{"city":"合肥","AQI":"141","quality":"轻度污染","pollutant":"颗粒物(PM2.5)","PM2.5":"107","PM10":"121","CO":"1.08","NO2":"21","O3":"264","O3_8h":"161","SO2":"12"},"临汾":{"city":"临汾","AQI":"141","quality":"轻度污染","pollutant":"臭氧8小时","PM2.5":"58","PM10":"67","CO":"0.9","NO2":"4","O3":"224","O3_8h":"203","SO2":"13"},"许昌":{"city":"许昌","AQI":"145","quality":"轻度污染","pollutant":"臭氧1小时","PM2.5":"60","PM10":"115","CO":"0.95","NO2":"14","O3":"287","O3_8h":"199","SO2":"22"},"新乡":{"city":"新乡","AQI":"146","quality":"轻度污染","pollutant":"臭氧1小时","PM2.5":"52","PM10":"142","CO":"0.825","NO2":"20","O3":"290","O3_8h":"199","SO2":"22"},"三门峡":{"city":"三门峡","AQI":"146","quality":"轻度污染","pollutant":"臭氧8小时","PM2.5":"47","PM10":"93","CO":"0.825","NO2":"15","O3":"265","O3_8h":"209","SO2":"19"},"邢台":{"city":"邢台","AQI":"148","quality":"轻度污染","pollutant":"颗粒物(PM2.5)","PM2.5":"113","PM10":"194","CO":"1.8","NO2":"46","O3":"277","O3_8h":"117","SO2":"51"},"长治":{"city":"长治","AQI":"150","quality":"轻度污染","pollutant":"臭氧8小时","PM2.5":"45","PM10":"84","CO":"0.64","NO2":"7","O3":"199","O3_8h":"214","SO2":"9"},"句容":{"city":"句容","AQI":"154","quality":"中度污染","pollutant":"颗粒物(PM10)","PM2.5":"76","PM10":"255","CO":"0.7","NO2":"24","O3":"175","O3_8h":"123","SO2":"22"},"开封":{"city":"开封","AQI":"156","quality":"中度污染","pollutant":"颗粒物(PM10)","PM2.5":"72","PM10":"259","CO":"0.775","NO2":"18","O3":"279","O3_8h":"176","SO2":"11"},"运城":{"city":"运城","AQI":"161","quality":"中度污染","pollutant":"臭氧8小时","PM2.5":"38","PM10":"79","CO":"0.78","NO2":"10","O3":"233","O3_8h":"225","SO2":"15"},"鹤壁":{"city":"鹤壁","AQI":"162","quality":"中度污染","pollutant":"臭氧1小时","PM2.5":"67","PM10":"156","CO":"1.167","NO2":"21","O3":"322","O3_8h":"196","SO2":"29"},"郑州":{"city":"郑州","AQI":"168","quality":"中度污染","pollutant":"臭氧1小时","PM2.5":"69","PM10":"167","CO":"1.0","NO2":"24","O3":"333","O3_8h":"184","SO2":"23"},"安阳":{"city":"安阳","AQI":"183","quality":"中度污染","pollutant":"臭氧1小时","PM2.5":"74","PM10":"180","CO":"1.58","NO2":"22","O3":"364","O3_8h":"207","SO2":"16"},"库尔勒":{"city":"库尔勒","AQI":"240","quality":"重度污染","pollutant":"颗粒物(PM10)","PM2.5":"163","PM10":"377","CO":"1.2","NO2":"11","O3":"71","O3_8h":"68","SO2":"4"},"嘉峪关":{"city":"嘉峪关","AQI":"500","quality":"严重污染","pollutant":"颗粒物(PM10)","PM2.5":"225","PM10":"926","CO":"0.5","NO2":"18","O3":"88","O3_8h":"91","SO2":"31"},"武威":{"city":"武威","AQI":"500","quality":"严重污染","pollutant":"颗粒物(PM10)","PM2.5":"227","PM10":"757","CO":"0.55","NO2":"20","O3":"66","O3_8h":"63","SO2":"3"},"金昌":{"city":"金昌","AQI":"500","quality":"严重污染","pollutant":"颗粒物(PM10)","PM2.5":"332","PM10":"1605","CO":"0.233","NO2":"5","O3":"105","O3_8h":"94","SO2":"7"},"和田地区":{"city":"和田地区","AQI":"500","quality":"严重污染","pollutant":"颗粒物(PM10)","PM2.5":"222","PM10":"1176","CO":"0.3","NO2":"5","O3":"109","O3_8h":"89","SO2":"25"},"酒泉":{"city":"酒泉","AQI":"500","quality":"严重污染","pollutant":"颗粒物(PM10)","PM2.5":"306","PM10":"1119","CO":"0.2","NO2":"5","O3":"97","O3_8h":"92","SO2":"2"},"呼和浩特":{"city":"呼和浩特","AQI":"500","quality":"严重污染","pollutant":"颗粒物(PM10)","PM2.5":"146","PM10":"712","CO":"0.457","NO2":"7","O3":"100","O3_8h":"89","SO2":"7"},"updateTime":"2017-06-02 14:00:00"}